pyemer/__init__.py
pyemer/authproxy.py
pyemer/main.py
pyemer/models.py
pyemer-0.1.0.dist-info/LICENSE
pyemer-0.1.0.dist-info/WHEEL
pyemer-0.1.0.dist-info/METADATA
pyemer-0.1.0.dist-info/RECORD
