Metadata-Version: 2.1
Name: pyemer
Version: 0.1.0
Summary: Python API for Emercoin blockchain.
Home-page: https://github.com/fire-squad/PyEmer
License: AGPL3
Author: Vasiliy Petrov
Author-email: cofob@riseup.net
Requires-Python: >=3.8,<4.0
Classifier: License :: Other/Proprietary License
Classifier: Programming Language :: Python :: 3
Classifier: Programming Language :: Python :: 3.10
Classifier: Programming Language :: Python :: 3.8
Classifier: Programming Language :: Python :: 3.9
Project-URL: Repository, https://github.com/fire-squad/PyEmer
